material_fingerprinting/Database.py
material_fingerprinting/Discover.py
material_fingerprinting/Experiment.py
material_fingerprinting/ExperimentUnion.py
material_fingerprinting/Fingerprints.py
material_fingerprinting/Kinematics.py
material_fingerprinting/Material.py
material_fingerprinting/Measurement.py
material_fingerprinting/__init__.py
material_fingerprinting/databases/DB_HEI.pkl
material_fingerprinting-0.1.4.dist-info/licenses/LICENSE
material_fingerprinting-0.1.4.dist-info/METADATA
material_fingerprinting-0.1.4.dist-info/WHEEL
material_fingerprinting-0.1.4.dist-info/top_level.txt
material_fingerprinting-0.1.4.dist-info/RECORD
